python_greek_names/__init__.py
python_greek_names/cli.py
python_greek_names/utils.py
python_greek_names-0.1.0.dist-info/DESCRIPTION.rst
python_greek_names-0.1.0.dist-info/METADATA
python_greek_names-0.1.0.dist-info/RECORD
python_greek_names-0.1.0.dist-info/WHEEL
python_greek_names-0.1.0.dist-info/entry_points.txt
python_greek_names-0.1.0.dist-info/metadata.json
python_greek_names-0.1.0.dist-info/top_level.txt
