Metadata-Version: 2.0
Name: python-greek-names
Version: 0.1.0
Summary: Python utils for working with names in Greek language.
Home-page: https://github.com/g20ready/python_greek_names
Author: Marsel Tzatzo
Author-email: tmarselg@gmail.com
License: MIT license
Keywords: python_greek_names
Platform: UNKNOWN
Classifier: Development Status :: 2 - Pre-Alpha
Classifier: Intended Audience :: Developers
Classifier: License :: OSI Approved :: MIT License
Classifier: Natural Language :: English
Classifier: Programming Language :: Python :: 2
Classifier: Programming Language :: Python :: 2.7
Classifier: Programming Language :: Python :: 3
Classifier: Programming Language :: Python :: 3.4
Classifier: Programming Language :: Python :: 3.5
Classifier: Programming Language :: Python :: 3.6
Requires-Dist: Click (>=6.0)
Requires-Dist: python-text-utils (>=0.0.6)
